Metadata-Version: 2.4
Name: torchguard
Version: 1.1.0
Summary: Compile-time error handling for torch.compile() regions
License: MIT
Project-URL: Homepage, https://github.com/yourusername/torchguard
Project-URL: Documentation, https://github.com/yourusername/torchguard#readme
Project-URL: Repository, https://github.com/yourusername/torchguard
Project-URL: Issues, https://github.com/yourusername/torchguard/issues
Project-URL: Changelog, https://github.com/yourusername/torchguard/blob/main/CHANGELOG.md
Keywords: pytorch,torch,compile,error-handling,machine-learning,deep-learning
Classifier: Development Status :: 3 - Alpha
Classifier: Intended Audience :: Developers
Classifier: Intended Audience :: Science/Research
Classifier: License :: OSI Approved :: MIT License
Classifier: Operating System :: OS Independent
Classifier: Programming Language :: Python :: 3
Classifier: Programming Language :: Python :: 3.9
Classifier: Programming Language :: Python :: 3.10
Classifier: Programming Language :: Python :: 3.11
Classifier: Programming Language :: Python :: 3.12
Classifier: Topic :: Scientific/Engineering
Classifier: Topic :: Scientific/Engineering :: Artificial Intelligence
Classifier: Topic :: Software Development :: Libraries :: Python Modules
Classifier: Typing :: Typed
Requires-Python: >=3.9
Requires-Dist: torch>=2.0.0
Requires-Dist: packaging
Provides-Extra: dev
Requires-Dist: pytest>=7.0; extra == "dev"
Requires-Dist: pytest-cov>=4.0; extra == "dev"
Provides-Extra: lint
Requires-Dist: black>=23.0; extra == "lint"
Requires-Dist: isort>=5.12; extra == "lint"
Requires-Dist: mypy>=1.0; extra == "lint"
Provides-Extra: all
Requires-Dist: torchguard[dev,lint]; extra == "all"
